EFumi_WhlTest/__init__.py
EFumi_WhlTest/core.py
EFumi_WhlTest/functions.py
EFumi_WhlTest/variables.py
EFumi_WhlTest-0.7.data/scripts/main.py
EFumi_WhlTest-0.7.dist-info/METADATA
EFumi_WhlTest-0.7.dist-info/WHEEL
EFumi_WhlTest-0.7.dist-info/top_level.txt
EFumi_WhlTest-0.7.dist-info/RECORD
