Metadata-Version: 2.1
Name: EFumi-WhlTest
Version: 0.7
Summary: A small example package
Home-page: https://github.com/pypa/sampleproject
Author: Erik Fumi
Author-email: erik12357@hotmail.com
License: UNKNOWN
Platform: UNKNOWN
Classifier: Programming Language :: Python :: 3
Classifier: License :: OSI Approved :: MIT License
Classifier: Operating System :: OS Independent
Requires-Python: >=3.6
Requires-Dist: numpy
